[
  {
    "id": "1782922088555_yn0hn",
    "time": "2026-07-01T16:08:08.555Z",
    "type": "Webhook Lost",
    "message": "Router connection lost. Last webhook received 5 minutes ago."
  },
  {
    "id": "1782922088546_mbe89",
    "time": "2026-07-01T16:08:08.546Z",
    "type": "User Offline",
    "message": "User user1 has disconnected."
  },
  {
    "id": "1782922088535_6g7dh",
    "time": "2026-07-01T16:08:08.535Z",
    "type": "Secret Key Invalid",
    "message": "Unauthorized webhook attempt ignored."
  },
  {
    "id": "1782922088530_528ik",
    "time": "2026-07-01T16:08:08.530Z",
    "type": "User Online",
    "message": "User user2 is now online."
  },
  {
    "id": "1782922088528_q4fo8",
    "time": "2026-07-01T16:08:08.528Z",
    "type": "User Online",
    "message": "User user1 is now online."
  },
  {
    "id": "1782922088524_iq779",
    "time": "2026-07-01T16:08:08.524Z",
    "type": "Router Restored",
    "message": "Router TestRouter has restored connection."
  },
  {
    "id": "1782922066622_yzvub",
    "time": "2026-07-01T16:07:46.622Z",
    "type": "Secret Key Invalid",
    "message": "Unauthorized webhook attempt ignored."
  },
  {
    "id": "1782921925615_34sge",
    "time": "2026-07-01T16:05:25.615Z",
    "type": "System Pause",
    "message": "System execution status changed to PAUSE."
  },
  {
    "id": "1782921848190_xzrqk",
    "time": "2026-07-01T16:04:08.190Z",
    "type": "User Offline",
    "message": "User user2 has disconnected."
  },
  {
    "id": "1782921780162_ry8f0",
    "time": "2026-07-01T16:03:00.162Z",
    "type": "Storage Recovered",
    "message": "Files recovered from backup: config.json"
  },
  {
    "id": "1782921780117_jkqlm",
    "time": "2026-07-01T16:03:00.117Z",
    "type": "Webhook Lost",
    "message": "Router connection lost. Last webhook received 5 minutes ago."
  },
  {
    "id": "1782921780110_mmpd5",
    "time": "2026-07-01T16:03:00.110Z",
    "type": "User Offline",
    "message": "User user1 has disconnected."
  },
  {
    "id": "1782921780093_9i6rj",
    "time": "2026-07-01T16:03:00.093Z",
    "type": "Secret Key Invalid",
    "message": "Unauthorized webhook attempt ignored."
  },
  {
    "id": "1782921780064_i3vxv",
    "time": "2026-07-01T16:03:00.064Z",
    "type": "User Online",
    "message": "User user2 is now online."
  },
  {
    "id": "1782921780054_f6tmc",
    "time": "2026-07-01T16:03:00.054Z",
    "type": "User Online",
    "message": "User user1 is now online."
  },
  {
    "id": "1782921780041_dft0k",
    "time": "2026-07-01T16:03:00.041Z",
    "type": "Router Restored",
    "message": "Router TestRouter has restored connection."
  }
]